autolaunch/__init__.py
autolaunch/autolaunch.py
autolaunch-1.0.9.dist-info/LICENSE
autolaunch-1.0.9.dist-info/METADATA
autolaunch-1.0.9.dist-info/WHEEL
autolaunch-1.0.9.dist-info/entry_points.txt
autolaunch-1.0.9.dist-info/top_level.txt
autolaunch-1.0.9.dist-info/RECORD
